<?xml version="1.0" ?>
<scene verion="0.5.0">
    <integrator type="path"/>
    <bsdf id="scene0546_00_wall" type="microfacet">
        <float name="uvScale" value="0.293"/>
        <texture name="albedo" type="bitmap">
            <string name="filename" value="../../../TileableTextureSynthesis/materials_50_modified/Material__parquet_european_ash_grey/tiled/diffuse_tiled.png"/>
        </texture>
        <rgb name="albedoScale" value="1.229 1.110 0.797"/>
        <texture name="normal" type="bitmap">
            <string name="filename" value="../../../TileableTextureSynthesis/materials_50_modified/Material__parquet_european_ash_grey/tiled/normal_tiled.png"/>
        </texture>
        <texture name="roughness" type="bitmap">
            <string name="filename" value="../../../TileableTextureSynthesis/materials_50_modified/Material__parquet_european_ash_grey/tiled/rough_tiled.png"/>
        </texture>
        <float name="roughnessScale" value="1.075"/>
    </bsdf>
    <bsdf id="scene0546_00_ceiling" type="microfacet">
        <float name="uvScale" value="0.293"/>
        <texture name="albedo" type="bitmap">
            <string name="filename" value="../../../TileableTextureSynthesis/materials_50_modified/Material__parquet_european_ash_grey/tiled/diffuse_tiled.png"/>
        </texture>
        <rgb name="albedoScale" value="1.253 0.962 1.079"/>
        <texture name="normal" type="bitmap">
            <string name="filename" value="../../../TileableTextureSynthesis/materials_50_modified/Material__parquet_european_ash_grey/tiled/normal_tiled.png"/>
        </texture>
        <texture name="roughness" type="bitmap">
            <string name="filename" value="../../../TileableTextureSynthesis/materials_50_modified/Material__parquet_european_ash_grey/tiled/rough_tiled.png"/>
        </texture>
        <float name="roughnessScale" value="1.034"/>
    </bsdf>
    <bsdf id="scene0546_00_floor" type="microfacet">
        <float name="uvScale" value="0.293"/>
        <texture name="albedo" type="bitmap">
            <string name="filename" value="../../../TileableTextureSynthesis/materials_50_modified/Material__aluminium_foil_rough_aluminium/tiled/diffuse_tiled.png"/>
        </texture>
        <rgb name="albedoScale" value="0.907 1.175 0.950"/>
        <texture name="normal" type="bitmap">
            <string name="filename" value="../../../TileableTextureSynthesis/materials_50_modified/Material__aluminium_foil_rough_aluminium/tiled/normal_tiled.png"/>
        </texture>
        <texture name="roughness" type="bitmap">
            <string name="filename" value="../../../TileableTextureSynthesis/materials_50_modified/Material__aluminium_foil_rough_aluminium/tiled/rough_tiled.png"/>
        </texture>
        <float name="roughnessScale" value="0.936"/>
    </bsdf>
    <shape id="scene0546_00_object" type="obj">
        <string name="filename" value="../../../../../layoutMesh/scene0546_00/uv_mapped.obj"/>
        <transform name="toWorld">
            <scale x="1.000000" y="1.000000" z="1.000000"/>
            <rotate angle="90.000000" x="-1.000000" y="0.000000" z="0.000000"/>
            <translate x="-1.442269" y="-1.071204" z="2.087512"/>
        </transform>
        <ref id="scene0546_00_wall" name="bsdf"/>
        <ref id="scene0546_00_ceiling" name="bsdf"/>
        <ref id="scene0546_00_floor" name="bsdf"/>
    </shape>
    <shape id="scene0546_00_object" type="obj">
        <string name="filename" value="../../../../../layoutMesh/scene0546_00/container.obj"/>
        <transform name="toWorld">
            <scale x="1.000000" y="1.000000" z="1.000000"/>
            <rotate angle="90.000000" x="-1.000000" y="0.000000" z="0.000000"/>
            <translate x="-1.442269" y="-1.071204" z="2.087512"/>
        </transform>
        <ref id="scene0546_00_wall" name="bsdf"/>
        <ref id="scene0546_00_ceiling" name="bsdf"/>
        <ref id="scene0546_00_floor" name="bsdf"/>
    </shape>
    <bsdf id="03001627_ae9e1ff1ae0b0a8f6ee473575a9f31bd_part0" type="microfacet">
        <float name="uvScale" value="0.755"/>
        <texture name="albedo" type="bitmap">
            <string name="filename" value="../../../TileableTextureSynthesis/materials_50_modified/Material__arabesque_tile_wall/tiled/diffuse_tiled.png"/>
        </texture>
        <rgb name="albedoScale" value="1.144 0.811 0.964"/>
        <texture name="normal" type="bitmap">
            <string name="filename" value="../../../TileableTextureSynthesis/materials_50_modified/Material__arabesque_tile_wall/tiled/normal_tiled.png"/>
        </texture>
        <texture name="roughness" type="bitmap">
            <string name="filename" value="../../../TileableTextureSynthesis/materials_50_modified/Material__arabesque_tile_wall/tiled/rough_tiled.png"/>
        </texture>
        <float name="roughnessScale" value="1.168"/>
    </bsdf>
    <shape id="03001627_ae9e1ff1ae0b0a8f6ee473575a9f31bd_object" type="obj">
        <string name="filename" value="../../../../../uv_mapped/03001627/ae9e1ff1ae0b0a8f6ee473575a9f31bd/alignedNew.obj"/>
        <transform name="toWorld">
            <scale x="1.142686" y="1.207821" z="0.997375"/>
            <rotate angle="7.997153" x="0.000000" y="1.000000" z="0.000000"/>
            <translate x="-0.099665" y="-0.787488" z="-0.523885"/>
            <translate x="0.000000" y="0.012079" z="0.000000"/>
        </transform>
        <ref id="03001627_ae9e1ff1ae0b0a8f6ee473575a9f31bd_part0" name="bsdf"/>
    </shape>
    <bsdf id="02933112_d3257b1df741d9a099c549327bba1953_part0" type="microfacet">
        <float name="uvScale" value="1.026"/>
        <texture name="albedo" type="bitmap">
            <string name="filename" value="../../../TileableTextureSynthesis/materials_50_modified/Material__ceramic_chamfered_tiles_english_subway/tiled/diffuse_tiled.png"/>
        </texture>
        <rgb name="albedoScale" value="0.709 1.106 1.261"/>
        <texture name="normal" type="bitmap">
            <string name="filename" value="../../../TileableTextureSynthesis/materials_50_modified/Material__ceramic_chamfered_tiles_english_subway/tiled/normal_tiled.png"/>
        </texture>
        <texture name="roughness" type="bitmap">
            <string name="filename" value="../../../TileableTextureSynthesis/materials_50_modified/Material__ceramic_chamfered_tiles_english_subway/tiled/rough_tiled.png"/>
        </texture>
        <float name="roughnessScale" value="0.843"/>
    </bsdf>
    <bsdf id="02933112_d3257b1df741d9a099c549327bba1953_part1" type="microfacet">
        <float name="uvScale" value="1.026"/>
        <texture name="albedo" type="bitmap">
            <string name="filename" value="../../../TileableTextureSynthesis/materials_50_modified/Material__aged_scratched_metal_dusty_old_gold/tiled/diffuse_tiled.png"/>
        </texture>
        <rgb name="albedoScale" value="1.174 0.934 0.962"/>
        <texture name="normal" type="bitmap">
            <string name="filename" value="../../../TileableTextureSynthesis/materials_50_modified/Material__aged_scratched_metal_dusty_old_gold/tiled/normal_tiled.png"/>
        </texture>
        <texture name="roughness" type="bitmap">
            <string name="filename" value="../../../TileableTextureSynthesis/materials_50_modified/Material__aged_scratched_metal_dusty_old_gold/tiled/rough_tiled.png"/>
        </texture>
        <float name="roughnessScale" value="0.833"/>
    </bsdf>
    <bsdf id="02933112_d3257b1df741d9a099c549327bba1953_part2" type="microfacet">
        <float name="uvScale" value="1.026"/>
        <texture name="albedo" type="bitmap">
            <string name="filename" value="../../../TileableTextureSynthesis/materials_50_modified/Material__wood_resin_filament_light_wood/tiled/diffuse_tiled.png"/>
        </texture>
        <rgb name="albedoScale" value="0.832 1.081 0.793"/>
        <texture name="normal" type="bitmap">
            <string name="filename" value="../../../TileableTextureSynthesis/materials_50_modified/Material__wood_resin_filament_light_wood/tiled/normal_tiled.png"/>
        </texture>
        <texture name="roughness" type="bitmap">
            <string name="filename" value="../../../TileableTextureSynthesis/materials_50_modified/Material__wood_resin_filament_light_wood/tiled/rough_tiled.png"/>
        </texture>
        <float name="roughnessScale" value="0.992"/>
    </bsdf>
    <bsdf id="02933112_d3257b1df741d9a099c549327bba1953_part3" type="microfacet">
        <float name="uvScale" value="1.026"/>
        <texture name="albedo" type="bitmap">
            <string name="filename" value="../../../TileableTextureSynthesis/materials_50_modified/Material__cotton_flannel_brushed/tiled/diffuse_tiled.png"/>
        </texture>
        <rgb name="albedoScale" value="1.106 0.755 0.787"/>
        <texture name="normal" type="bitmap">
            <string name="filename" value="../../../TileableTextureSynthesis/materials_50_modified/Material__cotton_flannel_brushed/tiled/normal_tiled.png"/>
        </texture>
        <texture name="roughness" type="bitmap">
            <string name="filename" value="../../../TileableTextureSynthesis/materials_50_modified/Material__cotton_flannel_brushed/tiled/rough_tiled.png"/>
        </texture>
        <float name="roughnessScale" value="0.900"/>
    </bsdf>
    <shape id="02933112_d3257b1df741d9a099c549327bba1953_object" type="obj">
        <string name="filename" value="../../../../../uv_mapped/02933112/d3257b1df741d9a099c549327bba1953/alignedNew.obj"/>
        <transform name="toWorld">
            <scale x="1.977434" y="2.530082" z="3.120925"/>
            <rotate angle="8.156101" x="0.000000" y="1.000000" z="0.000000"/>
            <translate x="0.736920" y="-0.330742" z="-0.471575"/>
            <translate x="0.000000" y="0.201994" z="0.000000"/>
        </transform>
        <ref id="02933112_d3257b1df741d9a099c549327bba1953_part0" name="bsdf"/>
        <ref id="02933112_d3257b1df741d9a099c549327bba1953_part1" name="bsdf"/>
        <ref id="02933112_d3257b1df741d9a099c549327bba1953_part2" name="bsdf"/>
        <ref id="02933112_d3257b1df741d9a099c549327bba1953_part3" name="bsdf"/>
    </shape>
    <bsdf id="02808440_d8c81bf718d534776b448b8aaebb705c_part0" type="microfacet">
        <float name="uvScale" value="1.223"/>
        <texture name="albedo" type="bitmap">
            <string name="filename" value="../../../TileableTextureSynthesis/materials_50_modified/Material__acetate_diffusion_ink_rain_forest_green/tiled/diffuse_tiled.png"/>
        </texture>
        <rgb name="albedoScale" value="0.851 1.009 1.132"/>
        <texture name="normal" type="bitmap">
            <string name="filename" value="../../../TileableTextureSynthesis/materials_50_modified/Material__acetate_diffusion_ink_rain_forest_green/tiled/normal_tiled.png"/>
        </texture>
        <texture name="roughness" type="bitmap">
            <string name="filename" value="../../../TileableTextureSynthesis/materials_50_modified/Material__acetate_diffusion_ink_rain_forest_green/tiled/rough_tiled.png"/>
        </texture>
        <float name="roughnessScale" value="0.951"/>
    </bsdf>
    <shape id="02808440_d8c81bf718d534776b448b8aaebb705c_object" type="obj">
        <string name="filename" value="../../../../../uv_mapped/02808440/d8c81bf718d534776b448b8aaebb705c/alignedNew.obj"/>
        <transform name="toWorld">
            <scale x="1.828871" y="1.358786" z="1.951385"/>
            <rotate angle="81.458996" x="0.000000" y="-1.000000" z="0.000000"/>
            <translate x="-0.933707" y="-0.874203" z="-0.902734"/>
            <translate x="0.000000" y="-0.019543" z="0.000000"/>
            <translate x="0.015388" y="0.000000" z="0.090615"/>
            <translate x="0.051115" y="0.000000" z="-0.008082"/>
        </transform>
        <ref id="02808440_d8c81bf718d534776b448b8aaebb705c_part0" name="bsdf"/>
    </shape>
    <bsdf id="door_1f131f6f97d53a283b5749d1b87fc99c_part0" type="microfacet">
        <float name="uvScale" value="1.244"/>
        <texture name="albedo" type="bitmap">
            <string name="filename" value="../../../TileableTextureSynthesis/materials_50_modified/Material__planks_cypress_nailed/tiled/diffuse_tiled.png"/>
        </texture>
        <rgb name="albedoScale" value="1.037 0.739 1.243"/>
        <texture name="normal" type="bitmap">
            <string name="filename" value="../../../TileableTextureSynthesis/materials_50_modified/Material__planks_cypress_nailed/tiled/normal_tiled.png"/>
        </texture>
        <texture name="roughness" type="bitmap">
            <string name="filename" value="../../../TileableTextureSynthesis/materials_50_modified/Material__planks_cypress_nailed/tiled/rough_tiled.png"/>
        </texture>
        <float name="roughnessScale" value="0.819"/>
    </bsdf>
    <bsdf id="door_1f131f6f97d53a283b5749d1b87fc99c_part1" type="microfacet">
        <float name="uvScale" value="1.244"/>
        <texture name="albedo" type="bitmap">
            <string name="filename" value="../../../TileableTextureSynthesis/materials_50_modified/Material__synthetic_suede_cell_embossed/tiled/diffuse_tiled.png"/>
        </texture>
        <rgb name="albedoScale" value="0.872 1.220 1.280"/>
        <texture name="normal" type="bitmap">
            <string name="filename" value="../../../TileableTextureSynthesis/materials_50_modified/Material__synthetic_suede_cell_embossed/tiled/normal_tiled.png"/>
        </texture>
        <texture name="roughness" type="bitmap">
            <string name="filename" value="../../../TileableTextureSynthesis/materials_50_modified/Material__synthetic_suede_cell_embossed/tiled/rough_tiled.png"/>
        </texture>
        <float name="roughnessScale" value="0.963"/>
    </bsdf>
    <bsdf id="window_2_part0" type="microfacet">
        <float name="uvScale" value="1.171"/>
        <texture name="albedo" type="bitmap">
            <string name="filename" value="../../../TileableTextureSynthesis/materials_50_modified/Material__linen_burlap_irregular/tiled/diffuse_tiled.png"/>
        </texture>
        <rgb name="albedoScale" value="0.721 1.196 1.164"/>
        <texture name="normal" type="bitmap">
            <string name="filename" value="../../../TileableTextureSynthesis/materials_50_modified/Material__linen_burlap_irregular/tiled/normal_tiled.png"/>
        </texture>
        <texture name="roughness" type="bitmap">
            <string name="filename" value="../../../TileableTextureSynthesis/materials_50_modified/Material__linen_burlap_irregular/tiled/rough_tiled.png"/>
        </texture>
        <float name="roughnessScale" value="0.996"/>
    </bsdf>
    <bsdf id="curtain_1_part0" type="microfacet">
        <float name="uvScale" value="0.858"/>
        <texture name="albedo" type="bitmap">
            <string name="filename" value="../../../TileableTextureSynthesis/materials_50_modified/Material__square_padded_wall_metallic_spaceship/tiled/diffuse_tiled.png"/>
        </texture>
        <rgb name="albedoScale" value="0.887 1.183 1.150"/>
        <texture name="normal" type="bitmap">
            <string name="filename" value="../../../TileableTextureSynthesis/materials_50_modified/Material__square_padded_wall_metallic_spaceship/tiled/normal_tiled.png"/>
        </texture>
        <texture name="roughness" type="bitmap">
            <string name="filename" value="../../../TileableTextureSynthesis/materials_50_modified/Material__square_padded_wall_metallic_spaceship/tiled/rough_tiled.png"/>
        </texture>
        <float name="roughnessScale" value="1.000"/>
    </bsdf>
    <bsdf id="curtain_1_part1" type="microfacet">
        <float name="uvScale" value="0.858"/>
        <texture name="albedo" type="bitmap">
            <string name="filename" value="../../../TileableTextureSynthesis/materials_50_modified/Material__silk_dense_duchesse_satin/tiled/diffuse_tiled.png"/>
        </texture>
        <rgb name="albedoScale" value="1.240 0.873 1.267"/>
        <texture name="normal" type="bitmap">
            <string name="filename" value="../../../TileableTextureSynthesis/materials_50_modified/Material__silk_dense_duchesse_satin/tiled/normal_tiled.png"/>
        </texture>
        <texture name="roughness" type="bitmap">
            <string name="filename" value="../../../TileableTextureSynthesis/materials_50_modified/Material__silk_dense_duchesse_satin/tiled/rough_tiled.png"/>
        </texture>
        <float name="roughnessScale" value="1.030"/>
    </bsdf>
    <shape id="ceiling_lamp_13357_object" type="obj">
        <string name="filename" value="../../../../../uv_mapped/ceiling_lamp/13357/alignedNew.obj"/>
        <emitter type="area">
<rgb value="69.2668495336028 205.3626970721665 785.9787031626576"/>
        </emitter>
        <transform name="toWorld">
            <scale x="0.249501" y="0.500000" z="0.249501"/>
            <rotate angle="90.000000" x="1.000000" y="-0.000000" z="-0.000000"/>
            <translate x="1.655646" y="1.586231" z="2.582000"/>
            <scale x="1.000000" y="1.000000" z="1.000000"/>
            <rotate angle="90.000000" x="-1.000000" y="0.000000" z="0.000000"/>
            <translate x="-1.442269" y="-1.071204" z="2.087512"/>
        </transform>
    </shape>
    <sensor type="perspective">
        <float name="fov" value="58.1403"/>
        <string name="fovAxis" value="x"/>
        <film type="hdrfilm">
            <integer name="width" value="640"/>
            <integer name="height" value="480"/>
        </film>
        <sampler type="adaptive">
            <integer name="sampleCount" value="1024"/>
        </sampler>
    </sensor>
    <emitter type="envmap">
        <string name="filename" value="../../../../../EnvDataset/178L.hdr"/>
        <float name="scale" value="0.00000001"/>
    </emitter>
</scene>
