<?xml version="1.0" ?>
<scene verion="0.5.0">
    <integrator type="path"/>
    <bsdf id="scene0549_00_wall" type="microfacet">
        <float name="uvScale" value="0.284"/>
        <texture name="albedo" type="bitmap">
            <string name="filename" value="../../../TileableTextureSynthesis/materials_50_5_modified/Material__church_wall_chamfered_cracks_brown_stone/tiled/diffuse_tiled.png"/>
        </texture>
        <rgb name="albedoScale" value="1.047 0.750 1.272"/>
        <texture name="normal" type="bitmap">
            <string name="filename" value="../../../TileableTextureSynthesis/materials_50_5_modified/Material__church_wall_chamfered_cracks_brown_stone/tiled/normal_tiled.png"/>
        </texture>
        <texture name="roughness" type="bitmap">
            <string name="filename" value="../../../TileableTextureSynthesis/materials_50_5_modified/Material__church_wall_chamfered_cracks_brown_stone/tiled/rough_tiled.png"/>
        </texture>
        <float name="roughnessScale" value="0.985"/>
    </bsdf>
    <bsdf id="scene0549_00_ceiling" type="microfacet">
        <float name="uvScale" value="0.284"/>
        <texture name="albedo" type="bitmap">
            <string name="filename" value="../../../TileableTextureSynthesis/materials_50_5_modified/Material__church_wall_chamfered_cracks_brown_stone/tiled/diffuse_tiled.png"/>
        </texture>
        <rgb name="albedoScale" value="1.099 0.913 0.931"/>
        <texture name="normal" type="bitmap">
            <string name="filename" value="../../../TileableTextureSynthesis/materials_50_5_modified/Material__church_wall_chamfered_cracks_brown_stone/tiled/normal_tiled.png"/>
        </texture>
        <texture name="roughness" type="bitmap">
            <string name="filename" value="../../../TileableTextureSynthesis/materials_50_5_modified/Material__church_wall_chamfered_cracks_brown_stone/tiled/rough_tiled.png"/>
        </texture>
        <float name="roughnessScale" value="1.002"/>
    </bsdf>
    <bsdf id="scene0549_00_floor" type="microfacet">
        <float name="uvScale" value="0.284"/>
        <texture name="albedo" type="bitmap">
            <string name="filename" value="../../../TileableTextureSynthesis/materials_50_5_modified/Material__acetate_beech_zebrano_spring_corn/tiled/diffuse_tiled.png"/>
        </texture>
        <rgb name="albedoScale" value="1.090 0.973 1.098"/>
        <texture name="normal" type="bitmap">
            <string name="filename" value="../../../TileableTextureSynthesis/materials_50_5_modified/Material__acetate_beech_zebrano_spring_corn/tiled/normal_tiled.png"/>
        </texture>
        <texture name="roughness" type="bitmap">
            <string name="filename" value="../../../TileableTextureSynthesis/materials_50_5_modified/Material__acetate_beech_zebrano_spring_corn/tiled/rough_tiled.png"/>
        </texture>
        <float name="roughnessScale" value="0.857"/>
    </bsdf>
    <shape id="scene0549_00_object" type="obj">
        <string name="filename" value="../../../../../layoutMesh/scene0549_00/uv_mapped.obj"/>
        <transform name="toWorld">
            <scale x="1.000000" y="1.000000" z="1.000000"/>
            <rotate angle="90.000000" x="-1.000000" y="0.000000" z="0.000000"/>
            <translate x="-3.825942" y="-0.669291" z="3.866603"/>
        </transform>
        <ref id="scene0549_00_wall" name="bsdf"/>
        <ref id="scene0549_00_ceiling" name="bsdf"/>
        <ref id="scene0549_00_floor" name="bsdf"/>
    </shape>
    <shape id="scene0549_00_object" type="obj">
        <string name="filename" value="../../../../../layoutMesh/scene0549_00/container.obj"/>
        <transform name="toWorld">
            <scale x="1.000000" y="1.000000" z="1.000000"/>
            <rotate angle="90.000000" x="-1.000000" y="0.000000" z="0.000000"/>
            <translate x="-3.825942" y="-0.669291" z="3.866603"/>
        </transform>
        <ref id="scene0549_00_wall" name="bsdf"/>
        <ref id="scene0549_00_ceiling" name="bsdf"/>
        <ref id="scene0549_00_floor" name="bsdf"/>
    </shape>
    <bsdf id="04256520_681d226acbeaaf08a4ee0fb6a51564c3_part0" type="microfacet">
        <float name="uvScale" value="1.138"/>
        <texture name="albedo" type="bitmap">
            <string name="filename" value="../../../TileableTextureSynthesis/materials_50_5_modified/Material__oil_asphalt_wet_asphalt/tiled/diffuse_tiled.png"/>
        </texture>
        <rgb name="albedoScale" value="0.888 1.076 1.008"/>
        <texture name="normal" type="bitmap">
            <string name="filename" value="../../../TileableTextureSynthesis/materials_50_5_modified/Material__oil_asphalt_wet_asphalt/tiled/normal_tiled.png"/>
        </texture>
        <texture name="roughness" type="bitmap">
            <string name="filename" value="../../../TileableTextureSynthesis/materials_50_5_modified/Material__oil_asphalt_wet_asphalt/tiled/rough_tiled.png"/>
        </texture>
        <float name="roughnessScale" value="1.057"/>
    </bsdf>
    <shape id="04256520_681d226acbeaaf08a4ee0fb6a51564c3_object" type="obj">
        <string name="filename" value="../../../../../uv_mapped/04256520/681d226acbeaaf08a4ee0fb6a51564c3/alignedNew.obj"/>
        <transform name="toWorld">
            <scale x="2.120169" y="1.740325" z="2.220931"/>
            <rotate angle="14.268686" x="0.000000" y="-1.000000" z="0.000000"/>
            <translate x="-1.232772" y="0.034289" z="2.800552"/>
            <translate x="0.000000" y="-0.277549" z="0.000000"/>
        </transform>
        <ref id="04256520_681d226acbeaaf08a4ee0fb6a51564c3_part0" name="bsdf"/>
    </shape>
    <bsdf id="03991062_cf184ee375cf827eeee0d5e82f0b9cab_part0" type="microfacet">
        <float name="uvScale" value="0.875"/>
        <texture name="albedo" type="bitmap">
            <string name="filename" value="../../../TileableTextureSynthesis/materials_50_5_modified/Material__arabesque_tile_wall_small_red_arabesque/tiled/diffuse_tiled.png"/>
        </texture>
        <rgb name="albedoScale" value="1.020 0.734 0.996"/>
        <texture name="normal" type="bitmap">
            <string name="filename" value="../../../TileableTextureSynthesis/materials_50_5_modified/Material__arabesque_tile_wall_small_red_arabesque/tiled/normal_tiled.png"/>
        </texture>
        <texture name="roughness" type="bitmap">
            <string name="filename" value="../../../TileableTextureSynthesis/materials_50_5_modified/Material__arabesque_tile_wall_small_red_arabesque/tiled/rough_tiled.png"/>
        </texture>
        <float name="roughnessScale" value="0.880"/>
    </bsdf>
    <bsdf id="03991062_cf184ee375cf827eeee0d5e82f0b9cab_part1" type="microfacet">
        <float name="uvScale" value="0.875"/>
        <texture name="albedo" type="bitmap">
            <string name="filename" value="../../../TileableTextureSynthesis/materials_50_5_modified/Material__arabesque_tile_wall_damaged_arabesque/tiled/diffuse_tiled.png"/>
        </texture>
        <rgb name="albedoScale" value="1.064 0.883 0.731"/>
        <texture name="normal" type="bitmap">
            <string name="filename" value="../../../TileableTextureSynthesis/materials_50_5_modified/Material__arabesque_tile_wall_damaged_arabesque/tiled/normal_tiled.png"/>
        </texture>
        <texture name="roughness" type="bitmap">
            <string name="filename" value="../../../TileableTextureSynthesis/materials_50_5_modified/Material__arabesque_tile_wall_damaged_arabesque/tiled/rough_tiled.png"/>
        </texture>
        <float name="roughnessScale" value="1.193"/>
    </bsdf>
    <shape id="03991062_cf184ee375cf827eeee0d5e82f0b9cab_object" type="obj">
        <string name="filename" value="../../../../../uv_mapped/03991062/cf184ee375cf827eeee0d5e82f0b9cab/alignedNew.obj"/>
        <transform name="toWorld">
            <scale x="1.441795" y="0.687999" z="1.456955"/>
            <rotate angle="129.151004" x="0.000000" y="-1.000000" z="0.000000"/>
            <translate x="1.083557" y="0.488731" z="-1.370534"/>
            <translate x="0.000000" y="-0.066542" z="0.000000"/>
        </transform>
        <ref id="03991062_cf184ee375cf827eeee0d5e82f0b9cab_part0" name="bsdf"/>
        <ref id="03991062_cf184ee375cf827eeee0d5e82f0b9cab_part1" name="bsdf"/>
    </shape>
    <bsdf id="03001627_3bbcd9e945c6ceb8d3c29b715a9f3afe_part0" type="microfacet">
        <float name="uvScale" value="0.703"/>
        <texture name="albedo" type="bitmap">
            <string name="filename" value="../../../TileableTextureSynthesis/materials_50_5_modified/Material__dmls_silver_mirror_polished_gold/tiled/diffuse_tiled.png"/>
        </texture>
        <rgb name="albedoScale" value="1.169 1.118 0.930"/>
        <texture name="normal" type="bitmap">
            <string name="filename" value="../../../TileableTextureSynthesis/materials_50_5_modified/Material__dmls_silver_mirror_polished_gold/tiled/normal_tiled.png"/>
        </texture>
        <texture name="roughness" type="bitmap">
            <string name="filename" value="../../../TileableTextureSynthesis/materials_50_5_modified/Material__dmls_silver_mirror_polished_gold/tiled/rough_tiled.png"/>
        </texture>
        <float name="roughnessScale" value="0.831"/>
    </bsdf>
    <bsdf id="03001627_3bbcd9e945c6ceb8d3c29b715a9f3afe_part1" type="microfacet">
        <float name="uvScale" value="0.703"/>
        <texture name="albedo" type="bitmap">
            <string name="filename" value="../../../TileableTextureSynthesis/materials_50_5_modified/Material__concrete_smooth_glossy/tiled/diffuse_tiled.png"/>
        </texture>
        <rgb name="albedoScale" value="1.141 0.813 1.056"/>
        <texture name="normal" type="bitmap">
            <string name="filename" value="../../../TileableTextureSynthesis/materials_50_5_modified/Material__concrete_smooth_glossy/tiled/normal_tiled.png"/>
        </texture>
        <texture name="roughness" type="bitmap">
            <string name="filename" value="../../../TileableTextureSynthesis/materials_50_5_modified/Material__concrete_smooth_glossy/tiled/rough_tiled.png"/>
        </texture>
        <float name="roughnessScale" value="0.968"/>
    </bsdf>
    <shape id="03001627_3bbcd9e945c6ceb8d3c29b715a9f3afe_object" type="obj">
        <string name="filename" value="../../../../../uv_mapped/03001627/3bbcd9e945c6ceb8d3c29b715a9f3afe/alignedNew.obj"/>
        <transform name="toWorld">
            <scale x="1.093485" y="1.565230" z="0.960306"/>
            <rotate angle="82.066544" x="0.000000" y="1.000000" z="0.000000"/>
            <translate x="0.939702" y="-0.075890" z="-0.493972"/>
            <translate x="0.000000" y="-0.103014" z="0.000000"/>
        </transform>
        <ref id="03001627_3bbcd9e945c6ceb8d3c29b715a9f3afe_part0" name="bsdf"/>
        <ref id="03001627_3bbcd9e945c6ceb8d3c29b715a9f3afe_part1" name="bsdf"/>
    </shape>
    <shape id="03001627_3bbcd9e945c6ceb8d3c29b715a9f3afe_object" type="obj">
        <string name="filename" value="../../../../../uv_mapped/03001627/3bbcd9e945c6ceb8d3c29b715a9f3afe/alignedNew.obj"/>
        <transform name="toWorld">
            <scale x="1.084054" y="1.585410" z="0.989035"/>
            <rotate angle="106.935524" x="0.000000" y="-1.000000" z="0.000000"/>
            <translate x="-2.238824" y="-0.028157" z="1.584570"/>
            <translate x="0.000000" y="-0.144425" z="0.000000"/>
        </transform>
        <ref id="03001627_3bbcd9e945c6ceb8d3c29b715a9f3afe_part0" name="bsdf"/>
        <ref id="03001627_3bbcd9e945c6ceb8d3c29b715a9f3afe_part1" name="bsdf"/>
    </shape>
    <shape id="03001627_3bbcd9e945c6ceb8d3c29b715a9f3afe_object" type="obj">
        <string name="filename" value="../../../../../uv_mapped/03001627/3bbcd9e945c6ceb8d3c29b715a9f3afe/alignedNew.obj"/>
        <transform name="toWorld">
            <scale x="1.129051" y="1.571654" z="0.976158"/>
            <rotate angle="72.911750" x="0.000000" y="1.000000" z="0.000000"/>
            <translate x="0.252263" y="-0.054779" z="2.177056"/>
            <translate x="0.000000" y="-0.122113" z="0.000000"/>
        </transform>
        <ref id="03001627_3bbcd9e945c6ceb8d3c29b715a9f3afe_part0" name="bsdf"/>
        <ref id="03001627_3bbcd9e945c6ceb8d3c29b715a9f3afe_part1" name="bsdf"/>
    </shape>
    <bsdf id="04379243_e97546c24cad95ee9eea323f522c6486_part0" type="microfacet">
        <float name="uvScale" value="0.745"/>
        <texture name="albedo" type="bitmap">
            <string name="filename" value="../../../TileableTextureSynthesis/materials_50_5_modified/Material__acetate_artistic_mixed_rain_forest_grey/tiled/diffuse_tiled.png"/>
        </texture>
        <rgb name="albedoScale" value="0.703 0.762 0.978"/>
        <texture name="normal" type="bitmap">
            <string name="filename" value="../../../TileableTextureSynthesis/materials_50_5_modified/Material__acetate_artistic_mixed_rain_forest_grey/tiled/normal_tiled.png"/>
        </texture>
        <texture name="roughness" type="bitmap">
            <string name="filename" value="../../../TileableTextureSynthesis/materials_50_5_modified/Material__acetate_artistic_mixed_rain_forest_grey/tiled/rough_tiled.png"/>
        </texture>
        <float name="roughnessScale" value="0.823"/>
    </bsdf>
    <bsdf id="04379243_e97546c24cad95ee9eea323f522c6486_part1" type="microfacet">
        <float name="uvScale" value="0.745"/>
        <texture name="albedo" type="bitmap">
            <string name="filename" value="../../../TileableTextureSynthesis/materials_50_5_modified/Material__dmd_metallic_fine/tiled/diffuse_tiled.png"/>
        </texture>
        <rgb name="albedoScale" value="0.901 1.270 1.006"/>
        <texture name="normal" type="bitmap">
            <string name="filename" value="../../../TileableTextureSynthesis/materials_50_5_modified/Material__dmd_metallic_fine/tiled/normal_tiled.png"/>
        </texture>
        <texture name="roughness" type="bitmap">
            <string name="filename" value="../../../TileableTextureSynthesis/materials_50_5_modified/Material__dmd_metallic_fine/tiled/rough_tiled.png"/>
        </texture>
        <float name="roughnessScale" value="1.094"/>
    </bsdf>
    <shape id="04379243_e97546c24cad95ee9eea323f522c6486_object" type="obj">
        <string name="filename" value="../../../../../uv_mapped/04379243/e97546c24cad95ee9eea323f522c6486/alignedNew.obj"/>
        <transform name="toWorld">
            <scale x="1.434512" y="1.180780" z="1.068121"/>
            <rotate angle="11.150487" x="0.000000" y="-1.000000" z="0.000000"/>
            <translate x="-0.292792" y="-0.338315" z="-0.809459"/>
            <translate x="0.000000" y="-0.067662" z="0.000000"/>
        </transform>
        <ref id="04379243_e97546c24cad95ee9eea323f522c6486_part0" name="bsdf"/>
        <ref id="04379243_e97546c24cad95ee9eea323f522c6486_part1" name="bsdf"/>
    </shape>
    <shape id="03001627_3bbcd9e945c6ceb8d3c29b715a9f3afe_object" type="obj">
        <string name="filename" value="../../../../../uv_mapped/03001627/3bbcd9e945c6ceb8d3c29b715a9f3afe/alignedNew.obj"/>
        <transform name="toWorld">
            <scale x="1.084346" y="1.556647" z="0.971542"/>
            <rotate angle="105.782802" x="0.000000" y="-1.000000" z="0.000000"/>
            <translate x="-1.548035" y="-0.130912" z="-0.928367"/>
            <translate x="0.000000" y="-0.050682" z="0.000000"/>
        </transform>
        <ref id="03001627_3bbcd9e945c6ceb8d3c29b715a9f3afe_part0" name="bsdf"/>
        <ref id="03001627_3bbcd9e945c6ceb8d3c29b715a9f3afe_part1" name="bsdf"/>
    </shape>
    <bsdf id="04256520_ef479941cb60405f8cbd400aa99bee96_part0" type="microfacet">
        <float name="uvScale" value="0.884"/>
        <texture name="albedo" type="bitmap">
            <string name="filename" value="../../../TileableTextureSynthesis/materials_50_5_modified/Material__acrylic_polyester_ray_waves/tiled/diffuse_tiled.png"/>
        </texture>
        <rgb name="albedoScale" value="0.876 1.070 0.752"/>
        <texture name="normal" type="bitmap">
            <string name="filename" value="../../../TileableTextureSynthesis/materials_50_5_modified/Material__acrylic_polyester_ray_waves/tiled/normal_tiled.png"/>
        </texture>
        <texture name="roughness" type="bitmap">
            <string name="filename" value="../../../TileableTextureSynthesis/materials_50_5_modified/Material__acrylic_polyester_ray_waves/tiled/rough_tiled.png"/>
        </texture>
        <float name="roughnessScale" value="1.019"/>
    </bsdf>
    <shape id="04256520_ef479941cb60405f8cbd400aa99bee96_object" type="obj">
        <string name="filename" value="../../../../../uv_mapped/04256520/ef479941cb60405f8cbd400aa99bee96/alignedNew.obj"/>
        <transform name="toWorld">
            <scale x="1.958420" y="2.431582" z="1.850704"/>
            <rotate angle="170.646642" x="0.000000" y="1.000000" z="0.000000"/>
            <translate x="-0.150783" y="-0.216456" z="-1.763930"/>
            <translate x="0.000000" y="-0.088098" z="0.000000"/>
        </transform>
        <ref id="04256520_ef479941cb60405f8cbd400aa99bee96_part0" name="bsdf"/>
    </shape>
    <bsdf id="04379243_68680849282fb0be21ec2f83d790ab97_part0" type="microfacet">
        <float name="uvScale" value="1.220"/>
        <texture name="albedo" type="bitmap">
            <string name="filename" value="../../../TileableTextureSynthesis/materials_50_5_modified/Material__sls_plastic_matte_blue/tiled/diffuse_tiled.png"/>
        </texture>
        <rgb name="albedoScale" value="1.092 0.755 0.801"/>
        <texture name="normal" type="bitmap">
            <string name="filename" value="../../../TileableTextureSynthesis/materials_50_5_modified/Material__sls_plastic_matte_blue/tiled/normal_tiled.png"/>
        </texture>
        <texture name="roughness" type="bitmap">
            <string name="filename" value="../../../TileableTextureSynthesis/materials_50_5_modified/Material__sls_plastic_matte_blue/tiled/rough_tiled.png"/>
        </texture>
        <float name="roughnessScale" value="1.177"/>
    </bsdf>
    <shape id="04379243_68680849282fb0be21ec2f83d790ab97_object" type="obj">
        <string name="filename" value="../../../../../uv_mapped/04379243/68680849282fb0be21ec2f83d790ab97/alignedNew.obj"/>
        <transform name="toWorld">
            <scale x="1.323853" y="1.455509" z="1.325394"/>
            <rotate angle="20.419350" x="0.000000" y="-1.000000" z="0.000000"/>
            <translate x="-0.894882" y="-0.367361" z="1.829394"/>
            <translate x="0.000000" y="-0.106310" z="0.000000"/>
        </transform>
        <ref id="04379243_68680849282fb0be21ec2f83d790ab97_part0" name="bsdf"/>
    </shape>
    <bsdf id="04379243_7dd4c0baac6c76703002761e7a3ba3bd_part0" type="microfacet">
        <float name="uvScale" value="1.272"/>
        <texture name="albedo" type="bitmap">
            <string name="filename" value="../../../TileableTextureSynthesis/materials_50_5_modified/Material__hair/tiled/diffuse_tiled.png"/>
        </texture>
        <rgb name="albedoScale" value="0.789 1.202 1.052"/>
        <texture name="normal" type="bitmap">
            <string name="filename" value="../../../TileableTextureSynthesis/materials_50_5_modified/Material__hair/tiled/normal_tiled.png"/>
        </texture>
        <texture name="roughness" type="bitmap">
            <string name="filename" value="../../../TileableTextureSynthesis/materials_50_5_modified/Material__hair/tiled/rough_tiled.png"/>
        </texture>
        <float name="roughnessScale" value="0.892"/>
    </bsdf>
    <bsdf id="04379243_7dd4c0baac6c76703002761e7a3ba3bd_part1" type="microfacet">
        <float name="uvScale" value="1.272"/>
        <texture name="albedo" type="bitmap">
            <string name="filename" value="../../../TileableTextureSynthesis/materials_50_5_modified/Material__synthetic_suede_worsted/tiled/diffuse_tiled.png"/>
        </texture>
        <rgb name="albedoScale" value="1.261 1.124 1.006"/>
        <texture name="normal" type="bitmap">
            <string name="filename" value="../../../TileableTextureSynthesis/materials_50_5_modified/Material__synthetic_suede_worsted/tiled/normal_tiled.png"/>
        </texture>
        <texture name="roughness" type="bitmap">
            <string name="filename" value="../../../TileableTextureSynthesis/materials_50_5_modified/Material__synthetic_suede_worsted/tiled/rough_tiled.png"/>
        </texture>
        <float name="roughnessScale" value="1.141"/>
    </bsdf>
    <bsdf id="04379243_7dd4c0baac6c76703002761e7a3ba3bd_part2" type="microfacet">
        <float name="uvScale" value="1.272"/>
        <texture name="albedo" type="bitmap">
            <string name="filename" value="../../../TileableTextureSynthesis/materials_50_5_modified/Material__concrete_smooth_cracked_white/tiled/diffuse_tiled.png"/>
        </texture>
        <rgb name="albedoScale" value="0.918 1.192 1.236"/>
        <texture name="normal" type="bitmap">
            <string name="filename" value="../../../TileableTextureSynthesis/materials_50_5_modified/Material__concrete_smooth_cracked_white/tiled/normal_tiled.png"/>
        </texture>
        <texture name="roughness" type="bitmap">
            <string name="filename" value="../../../TileableTextureSynthesis/materials_50_5_modified/Material__concrete_smooth_cracked_white/tiled/rough_tiled.png"/>
        </texture>
        <float name="roughnessScale" value="0.829"/>
    </bsdf>
    <shape id="04379243_7dd4c0baac6c76703002761e7a3ba3bd_object" type="obj">
        <string name="filename" value="../../../../../uv_mapped/04379243/7dd4c0baac6c76703002761e7a3ba3bd/alignedNew.obj"/>
        <transform name="toWorld">
            <scale x="1.653009" y="1.893119" z="1.737991"/>
            <rotate angle="73.604373" x="0.000000" y="1.000000" z="0.000000"/>
            <translate x="1.156214" y="0.018738" z="2.713539"/>
            <translate x="0.000000" y="-0.171018" z="0.000000"/>
        </transform>
        <ref id="04379243_7dd4c0baac6c76703002761e7a3ba3bd_part0" name="bsdf"/>
        <ref id="04379243_7dd4c0baac6c76703002761e7a3ba3bd_part1" name="bsdf"/>
        <ref id="04379243_7dd4c0baac6c76703002761e7a3ba3bd_part2" name="bsdf"/>
    </shape>
    <bsdf id="04379243_c5178a8a0da618a25d78ff7fb413274d_part0" type="microfacet">
        <float name="uvScale" value="1.078"/>
        <texture name="albedo" type="bitmap">
            <string name="filename" value="../../../TileableTextureSynthesis/materials_50_5_modified/Material__gold_leaf_fold_fold_blur/tiled/diffuse_tiled.png"/>
        </texture>
        <rgb name="albedoScale" value="1.158 0.878 1.207"/>
        <texture name="normal" type="bitmap">
            <string name="filename" value="../../../TileableTextureSynthesis/materials_50_5_modified/Material__gold_leaf_fold_fold_blur/tiled/normal_tiled.png"/>
        </texture>
        <texture name="roughness" type="bitmap">
            <string name="filename" value="../../../TileableTextureSynthesis/materials_50_5_modified/Material__gold_leaf_fold_fold_blur/tiled/rough_tiled.png"/>
        </texture>
        <float name="roughnessScale" value="0.936"/>
    </bsdf>
    <shape id="04379243_c5178a8a0da618a25d78ff7fb413274d_object" type="obj">
        <string name="filename" value="../../../../../uv_mapped/04379243/c5178a8a0da618a25d78ff7fb413274d/alignedNew.obj"/>
        <transform name="toWorld">
            <scale x="0.951062" y="1.303654" z="1.063796"/>
            <rotate angle="84.827041" x="0.000000" y="1.000000" z="0.000000"/>
            <translate x="-2.466048" y="-0.063890" z="2.253296"/>
            <translate x="0.000000" y="-0.225907" z="0.000000"/>
        </transform>
        <ref id="04379243_c5178a8a0da618a25d78ff7fb413274d_part0" name="bsdf"/>
    </shape>
    <shape id="04379243_c5178a8a0da618a25d78ff7fb413274d_object" type="obj">
        <string name="filename" value="../../../../../uv_mapped/04379243/c5178a8a0da618a25d78ff7fb413274d/alignedNew.obj"/>
        <transform name="toWorld">
            <scale x="1.091527" y="1.306714" z="1.092094"/>
            <rotate angle="34.423409" x="0.000000" y="-1.000000" z="0.000000"/>
            <translate x="1.027094" y="-0.160811" z="-1.403265"/>
            <translate x="0.000000" y="-0.128096" z="0.000000"/>
        </transform>
        <ref id="04379243_c5178a8a0da618a25d78ff7fb413274d_part0" name="bsdf"/>
    </shape>
    <shape id="04379243_c5178a8a0da618a25d78ff7fb413274d_object" type="obj">
        <string name="filename" value="../../../../../uv_mapped/04379243/c5178a8a0da618a25d78ff7fb413274d/alignedNew.obj"/>
        <transform name="toWorld">
            <scale x="1.080393" y="1.295028" z="1.040748"/>
            <rotate angle="9.762349" x="0.000000" y="1.000000" z="0.000000"/>
            <translate x="-1.576076" y="-0.234077" z="-1.813379"/>
            <translate x="0.000000" y="-0.058232" z="0.000000"/>
            <translate x="0.053841" y="0.000000" z="0.012515"/>
        </transform>
        <ref id="04379243_c5178a8a0da618a25d78ff7fb413274d_part0" name="bsdf"/>
    </shape>
    <bsdf id="door_1db44c1324b42ef55f5890493271969b_part0" type="microfacet">
        <float name="uvScale" value="0.800"/>
        <texture name="albedo" type="bitmap">
            <string name="filename" value="../../../TileableTextureSynthesis/materials_50_5_modified/Material__synthetic_flowery_jersey_quilted_matte/tiled/diffuse_tiled.png"/>
        </texture>
        <rgb name="albedoScale" value="1.177 1.148 0.706"/>
        <texture name="normal" type="bitmap">
            <string name="filename" value="../../../TileableTextureSynthesis/materials_50_5_modified/Material__synthetic_flowery_jersey_quilted_matte/tiled/normal_tiled.png"/>
        </texture>
        <texture name="roughness" type="bitmap">
            <string name="filename" value="../../../TileableTextureSynthesis/materials_50_5_modified/Material__synthetic_flowery_jersey_quilted_matte/tiled/rough_tiled.png"/>
        </texture>
        <float name="roughnessScale" value="1.072"/>
    </bsdf>
    <bsdf id="door_1db44c1324b42ef55f5890493271969b_part1" type="microfacet">
        <float name="uvScale" value="0.800"/>
        <texture name="albedo" type="bitmap">
            <string name="filename" value="../../../TileableTextureSynthesis/materials_50_5_modified/Material__wallpaper_simple/tiled/diffuse_tiled.png"/>
        </texture>
        <rgb name="albedoScale" value="0.704 1.162 1.079"/>
        <texture name="normal" type="bitmap">
            <string name="filename" value="../../../TileableTextureSynthesis/materials_50_5_modified/Material__wallpaper_simple/tiled/normal_tiled.png"/>
        </texture>
        <texture name="roughness" type="bitmap">
            <string name="filename" value="../../../TileableTextureSynthesis/materials_50_5_modified/Material__wallpaper_simple/tiled/rough_tiled.png"/>
        </texture>
        <float name="roughnessScale" value="0.804"/>
    </bsdf>
    <bsdf id="window_3_part0" type="microfacet">
        <float name="uvScale" value="0.917"/>
        <texture name="albedo" type="bitmap">
            <string name="filename" value="../../../TileableTextureSynthesis/materials_50_5_modified/Material__iron_bumped/tiled/diffuse_tiled.png"/>
        </texture>
        <rgb name="albedoScale" value="1.151 0.744 1.038"/>
        <texture name="normal" type="bitmap">
            <string name="filename" value="../../../TileableTextureSynthesis/materials_50_5_modified/Material__iron_bumped/tiled/normal_tiled.png"/>
        </texture>
        <texture name="roughness" type="bitmap">
            <string name="filename" value="../../../TileableTextureSynthesis/materials_50_5_modified/Material__iron_bumped/tiled/rough_tiled.png"/>
        </texture>
        <float name="roughnessScale" value="1.172"/>
    </bsdf>
    <bsdf id="curtain_1_part0" type="microfacet">
        <float name="uvScale" value="0.994"/>
        <texture name="albedo" type="bitmap">
            <string name="filename" value="../../../TileableTextureSynthesis/materials_50_5_modified/Material__concrete_eroded/tiled/diffuse_tiled.png"/>
        </texture>
        <rgb name="albedoScale" value="1.111 0.871 1.064"/>
        <texture name="normal" type="bitmap">
            <string name="filename" value="../../../TileableTextureSynthesis/materials_50_5_modified/Material__concrete_eroded/tiled/normal_tiled.png"/>
        </texture>
        <texture name="roughness" type="bitmap">
            <string name="filename" value="../../../TileableTextureSynthesis/materials_50_5_modified/Material__concrete_eroded/tiled/rough_tiled.png"/>
        </texture>
        <float name="roughnessScale" value="1.023"/>
    </bsdf>
    <bsdf id="curtain_1_part1" type="microfacet">
        <float name="uvScale" value="0.994"/>
        <texture name="albedo" type="bitmap">
            <string name="filename" value="../../../TileableTextureSynthesis/materials_50_5_modified/Material__roughcast_troweled/tiled/diffuse_tiled.png"/>
        </texture>
        <rgb name="albedoScale" value="1.214 0.817 0.959"/>
        <texture name="normal" type="bitmap">
            <string name="filename" value="../../../TileableTextureSynthesis/materials_50_5_modified/Material__roughcast_troweled/tiled/normal_tiled.png"/>
        </texture>
        <texture name="roughness" type="bitmap">
            <string name="filename" value="../../../TileableTextureSynthesis/materials_50_5_modified/Material__roughcast_troweled/tiled/rough_tiled.png"/>
        </texture>
        <float name="roughnessScale" value="1.009"/>
    </bsdf>
    <bsdf id="ceiling_lamp_15650_part1" type="microfacet">
        <float name="uvScale" value="1.087"/>
        <texture name="albedo" type="bitmap">
            <string name="filename" value="../../../TileableTextureSynthesis/materials_50_5_modified/Material__acoustic_foam_metallic_acoustic_foam/tiled/diffuse_tiled.png"/>
        </texture>
        <rgb name="albedoScale" value="0.886 1.270 0.930"/>
        <texture name="normal" type="bitmap">
            <string name="filename" value="../../../TileableTextureSynthesis/materials_50_5_modified/Material__acoustic_foam_metallic_acoustic_foam/tiled/normal_tiled.png"/>
        </texture>
        <texture name="roughness" type="bitmap">
            <string name="filename" value="../../../TileableTextureSynthesis/materials_50_5_modified/Material__acoustic_foam_metallic_acoustic_foam/tiled/rough_tiled.png"/>
        </texture>
        <float name="roughnessScale" value="0.971"/>
    </bsdf>
    <shape id="ceiling_lamp_15650_object" type="obj">
        <string name="filename" value="../../../../../uv_mapped/ceiling_lamp/15650/aligned_shape.obj"/>
        <transform name="toWorld">
            <scale x="1.096491" y="0.500000" z="1.096491"/>
            <rotate angle="90.000000" x="1.000000" y="0.000000" z="-0.000000"/>
            <translate x="4.050469" y="3.178846" z="2.496500"/>
            <scale x="1.000000" y="1.000000" z="1.000000"/>
            <rotate angle="90.000000" x="-1.000000" y="0.000000" z="0.000000"/>
            <translate x="-3.825942" y="-0.669291" z="3.866603"/>
        </transform>
        <ref id="ceiling_lamp_15650_part1" name="bsdf"/>
    </shape>
    <shape id="ceiling_lamp_15650_object" type="obj">
        <string name="filename" value="../../../../../uv_mapped/ceiling_lamp/15650/aligned_light.obj"/>
        <transform name="toWorld">
            <scale x="1.096491" y="0.500000" z="1.096491"/>
            <rotate angle="90.000000" x="1.000000" y="0.000000" z="-0.000000"/>
            <translate x="4.050469" y="3.178846" z="2.496500"/>
            <scale x="1.000000" y="1.000000" z="1.000000"/>
            <rotate angle="90.000000" x="-1.000000" y="0.000000" z="0.000000"/>
            <translate x="-3.825942" y="-0.669291" z="3.866603"/>
        </transform>
    </shape>
    <shape id="window_3_object" type="obj">
        <string name="filename" value="../../../../../uv_mapped/window/3/alignedNew.obj"/>
        <transform name="toWorld">
            <scale x="0.308446" y="0.598985" z="1.278234"/>
            <rotate angle="113.265237" x="0.658562" y="0.532117" z="0.532117"/>
            <translate x="14.155006" y="-1.686758" z="0.797083"/>
            <scale x="1.000000" y="1.000000" z="1.000000"/>
            <rotate angle="90.000000" x="-1.000000" y="0.000000" z="0.000000"/>
            <translate x="-3.825942" y="-0.669291" z="3.866603"/>
        </transform>
        <ref id="window_3_part0" name="bsdf"/>
    </shape>
    <shape id="door_1db44c1324b42ef55f5890493271969b_object" type="obj">
        <string name="filename" value="../../../../../uv_mapped/door/1db44c1324b42ef55f5890493271969b/alignedNew.obj"/>
        <transform name="toWorld">
            <scale x="2.127595" y="1.162646" z="2.125318"/>
            <rotate angle="127.229693" x="0.496081" y="-0.613964" z="-0.613964"/>
            <translate x="6.776378" y="2.606927" z="0.988243"/>
            <scale x="1.000000" y="1.000000" z="1.000000"/>
            <rotate angle="90.000000" x="-1.000000" y="0.000000" z="0.000000"/>
            <translate x="-3.825942" y="-0.669291" z="3.866603"/>
        </transform>
        <ref id="door_1db44c1324b42ef55f5890493271969b_part0" name="bsdf"/>
        <ref id="door_1db44c1324b42ef55f5890493271969b_part1" name="bsdf"/>
    </shape>
    <sensor type="perspective">
        <float name="fov" value="57.6146"/>
        <string name="fovAxis" value="x"/>
        <film type="hdrfilm">
            <integer name="width" value="640"/>
            <integer name="height" value="480"/>
        </film>
        <sampler type="adaptive">
            <integer name="sampleCount" value="1024"/>
        </sampler>
    </sensor>
    <emitter type="envmap">
        <string name="filename" value="../../../../../EnvDataset/56L.hdr"/>
        <float name="scale" value="181.1807"/>
    </emitter>
</scene>
